<?xml version="1.0" encoding="UTF-8"?>
<!-- SCORM 2004 4th Edition manifest - GENERATED FILE - DO NOT EDIT MANUALLY
     This file is automatically generated during build from course-config.js
     To modify course metadata or structure, edit scorm_template/course/course-config.js -->
<manifest identifier="SCORM-Template"
            version="2.0.0"
            xmlns="http://www.imsglobal.org/xsd/imscp_v1p1"
            xmlns:imscp="http://www.imsglobal.org/xsd/imscp_v1p1"
            xmlns:imsss="http://www.imsglobal.org/xsd/imsss"
            xmlns:adlcp="http://www.adlnet.org/xsd/adlcp_v1p3"
            xmlns:adlseq="http://www.adlnet.org/xsd/adlseq_v1p3"
            xmlns:adlnav="http://www.adlnet.org/xsd/adlnav_v1p3"
            xmlns:lom="http://ltsc.ieee.org/xsd/LOM"
            xmlns:xsi="http://www.w3.org/2001/XMLSchema-instance"
            xsi:schemaLocation="
              http://www.imsglobal.org/xsd/imscp_v1p1 imscp_v1p1.xsd
              http://www.imsglobal.org/xsd/imsss imsss_v1p0.xsd
              http://www.adlnet.org/xsd/adlcp_v1p3 adlcp_v1p3.xsd
              http://www.adlnet.org/xsd/adlseq_v1p3 adlseq_v1p3.xsd
              http://www.adlnet.org/xsd/adlnav_v1p3 adlnav_v1p3.xsd
              http://ltsc.ieee.org/xsd/LOM lom.xsd"
            xml:base="./">

  <metadata>
    <schema>ADL SCORM</schema>
    <schemaversion>2004 4th Edition</schemaversion>
    <lom:lom>
      <lom:general>
        <lom:title><lom:string language="en">SCORM Template</lom:string></lom:title>
        <lom:description><lom:string language="en">text</lom:string></lom:description>
        <lom:language>en</lom:language>
        <lom:identifier>
          <lom:catalog>URI</lom:catalog>
          <lom:entry>urn:scorm-template:2.0.0</lom:entry>
        </lom:identifier>
        <lom:keyword>
          <lom:string language="en">SCORM</lom:string>
        </lom:keyword>
        <lom:keyword>
          <lom:string language="en">eLearning</lom:string>
        </lom:keyword>
      </lom:general>
      <lom:lifecycle>
        <lom:version><lom:string>2.0.0</lom:string></lom:version>
        <lom:status>
          <lom:source><lom:string>LOMv1.0</lom:string></lom:source>
          <lom:value><lom:string>final</lom:string></lom:value>
        </lom:status>
        <lom:contribute>
          <lom:role>
            <lom:source><lom:string>LOMv1.0</lom:string></lom:source>
            <lom:value><lom:string>author</lom:string></lom:value>
          </lom:role>
          <lom:entity>Seth Vincent</lom:entity>
          <lom:date>
            <lom:dateTime>2025-11-21T15:47:52.609Z</lom:dateTime>
          </lom:date>
        </lom:contribute>
      </lom:lifecycle>
      <lom:educational>
        <lom:interactivityType>
          <lom:source><lom:string>LOMv1.0</lom:string></lom:source>
          <lom:value><lom:string>active</lom:string></lom:value>
        </lom:interactivityType>
        <lom:learningResourceType>
          <lom:source><lom:string>LOMv1.0</lom:string></lom:source>
          <lom:value><lom:string>exercise</lom:string></lom:value>
        </lom:learningResourceType>
        <lom:interactivityLevel>
          <lom:source><lom:string>LOMv1.0</lom:string></lom:source>
          <lom:value><lom:string>high</lom:string></lom:value>
        </lom:interactivityLevel>
        <lom:intendedEndUserRole>
          <lom:source><lom:string>LOMv1.0</lom:string></lom:source>
          <lom:value><lom:string>learner</lom:string></lom:value>
        </lom:intendedEndUserRole>
        <lom:context>
          <lom:source><lom:string>LOMv1.0</lom:string></lom:source>
          <lom:value><lom:string>training</lom:string></lom:value>
        </lom:context>
        <lom:typicalAgeRange>
          <lom:string language="en">18-99 years</lom:string>
        </lom:typicalAgeRange>
        <lom:description>
          <lom:string language="en">text</lom:string>
        </lom:description>
      </lom:educational>
      <lom:technical>
        <lom:format>text/html</lom:format>
        <lom:size>0</lom:size>
        <lom:location>
          <lom:string language="en">index.html</lom:string>
        </lom:location>
        <lom:requirement>
          <lom:orComposite>
            <lom:type>
              <lom:source><lom:string>LOMv1.0</lom:string></lom:source>
              <lom:value><lom:string>browser</lom:string></lom:value>
            </lom:type>
            <lom:name>
              <lom:source><lom:string>LOMv1.0</lom:string></lom:source>
              <lom:value><lom:string>any</lom:string></lom:value>
            </lom:name>
          </lom:orComposite>
        </lom:requirement>
        <lom:installationRemarks>
          <lom:string language="en">No special installation required.</lom:string>
        </lom:installationRemarks>
        <lom:otherPlatformRequirements>
          <lom:string language="en">SCORM 2004 4th Edition compliant LMS.</lom:string>
        </lom:otherPlatformRequirements>
      </lom:technical>
      <lom:rights>
        <lom:cost>
          <lom:source><lom:string>LOMv1.0</lom:string></lom:source>
          <lom:value><lom:string>no</lom:string></lom:value>
        </lom:cost>
        <lom:copyrightAndOtherRestrictions>
          <lom:source><lom:string>LOMv1.0</lom:string></lom:source>
          <lom:value><lom:string>yes</lom:string></lom:value>
        </lom:copyrightAndOtherRestrictions>
        <lom:description>
          <lom:string language="en">Copyright (c) 2025 Seth Vincent</lom:string>
        </lom:description>
      </lom:rights>
    </lom:lom>
  </metadata>

  <organizations default="org-1">
    <organization identifier="org-1" adlseq:objectivesGlobalToSystem="false" adlcp:sharedDataGlobalToSystem="false">
      <title>SCORM Template</title>

      <!-- Global Objectives for shared data mapping -->
      <adlseq:objectives>
        <adlseq:objective objectiveID="obj-global-completion">
          <adlseq:mapInfo targetObjectiveID="primary-objective" readSatisfiedStatus="true" writeSatisfiedStatus="false"/>
        </adlseq:objective>
        <adlseq:objective objectiveID="obj-global-success">
          <adlseq:mapInfo targetObjectiveID="primary-objective" readSatisfiedStatus="true" writeSatisfiedStatus="false"/>
        </adlseq:objective>
      </adlseq:objectives>

      <!-- Data store mapping for shared data -->
      <adlcp:data>
        <adlcp:map targetID="shared_runtime_data" readSharedData="true" writeSharedData="true"/>
        <adlcp:map targetID="learner_preferences" readSharedData="true" writeSharedData="true"/>
      </adlcp:data>

      <item identifier="item-1" identifierref="res-1" isvisible="true">
        <title>SCORM Template</title>
        <adlcp:completionThreshold completedByMeasure="true" minProgressMeasure="1.0" progressWeight="1.0"/>
        <imsss:sequencing>
          <imsss:controlMode choiceExit="true" forwardOnly="false"/>
          <imsss:deliveryControls tracked="true" completionSetByContent="true" objectiveSetByContent="true"/>

          <imsss:sequencingRules>
            <imsss:preConditionRule>
              <imsss:ruleConditions conditionCombination="any">
                <imsss:ruleCondition condition="satisfied" objectiveID="obj-global-completion" operator="not"/>
                <imsss:ruleCondition condition="attemptLimitExceeded"/>
              </imsss:ruleConditions>
              <imsss:ruleAction action="disabled"/>
            </imsss:preConditionRule>

            <imsss:preConditionRule>
              <imsss:ruleConditions>
                <imsss:ruleCondition condition="objectiveStatusKnown" objectiveID="primary-objective"/>
                <imsss:ruleCondition condition="satisfied" objectiveID="primary-objective"/>
              </imsss:ruleConditions>
              <imsss:ruleAction action="skip"/>
            </imsss:preConditionRule>

            <imsss:postConditionRule>
              <imsss:ruleConditions>
                <imsss:ruleCondition condition="satisfied" objectiveID="primary-objective"/>
              </imsss:ruleConditions>
              <imsss:ruleAction action="exitParent"/>
            </imsss:postConditionRule>

            <imsss:postConditionRule>
              <imsss:ruleConditions>
                <imsss:ruleCondition condition="objectiveStatusKnown" objectiveID="primary-objective"/>
                <imsss:ruleCondition condition="satisfied" objectiveID="primary-objective" operator="not"/>
                <imsss:ruleCondition condition="attemptLimitExceeded" operator="not"/>
              </imsss:ruleConditions>
              <imsss:ruleAction action="retry"/>
            </imsss:postConditionRule>
          </imsss:sequencingRules>

          <imsss:objectives>
            <imsss:primaryObjective objectiveID="primary-objective" satisfiedByMeasure="false">
              <imsss:mapInfo targetObjectiveID="obj-global-completion" readSatisfiedStatus="true" writeSatisfiedStatus="true"/>
            </imsss:primaryObjective>
            <imsss:objective objectiveID="assessment-completion">
              <imsss:mapInfo targetObjectiveID="obj-global-completion" readSatisfiedStatus="true" writeSatisfiedStatus="false"/>
            </imsss:objective>
          </imsss:objectives>

          <adlnav:presentation>
            <adlnav:navigationInterface>
              <adlnav:hideLMSUI>continue</adlnav:hideLMSUI>
              <adlnav:hideLMSUI>previous</adlnav:hideLMSUI>
              <adlnav:hideLMSUI>exit</adlnav:hideLMSUI>
              <adlnav:hideLMSUI>exitAll</adlnav:hideLMSUI>
              <adlnav:hideLMSUI>abandon</adlnav:hideLMSUI>
              <adlnav:hideLMSUI>abandonAll</adlnav:hideLMSUI>
              <adlnav:hideLMSUI>suspendAll</adlnav:hideLMSUI>
              <adlnav:hideLMSUI>toc</adlnav:hideLMSUI>
            </adlnav:navigationInterface>
          </adlnav:presentation>
          <imsss:presentation>
            <imsss:window width="1024" height="768"/>
          </imsss:presentation>
        </imsss:sequencing>
      </item>
    </organization>
  </organizations>

  <resources>
    <resource identifier="res-1" type="webcontent" adlcp:scormType="sco" href="index.html">
      <file href="index.html"/>
    </resource>
  </resources>
</manifest>
